pycalculator/__init__.py
pycalculator/advanced.py
pycalculator/basic.py
pycalculator/constants.py
pycalculator/trig.py
pycalculator_aniket-0.1.1.dist-info/licenses/LICENSE
pycalculator_aniket-0.1.1.dist-info/METADATA
pycalculator_aniket-0.1.1.dist-info/WHEEL
pycalculator_aniket-0.1.1.dist-info/top_level.txt
pycalculator_aniket-0.1.1.dist-info/RECORD
