Metadata-Version: 2.4
Name: pycalculator-aniket
Version: 0.1.1
Summary: A full-featured Python calculator package
Home-page: https://github.com/aniket-patidar01/py
Author: Aniket Patidar
Author-email: aniketpatidar70@gmail.com
Classifier: Programming Language :: Python :: 3
License-File: LICENSE
Dynamic: author
Dynamic: author-email
Dynamic: classifier
Dynamic: home-page
Dynamic: license-file
Dynamic: summary
